pypdb/__init__.py
pypdb/conftest.py
pypdb/pypdb.py
pypdb/clients/__init__.py
pypdb/clients/data/__init__.py
pypdb/clients/data/data_types.py
pypdb/clients/data/test_data_types.py
pypdb/clients/data/graphql/__init__.py
pypdb/clients/data/graphql/graphql.py
pypdb/clients/data/graphql/test_graphql.py
pypdb/clients/fasta/__init__.py
pypdb/clients/fasta/fasta_client.py
pypdb/clients/fasta/fasta_client_test.py
pypdb/clients/pdb/__init__.py
pypdb/clients/pdb/pdb_client.py
pypdb/clients/pdb/pdb_client_test.py
pypdb/clients/search/__init__.py
pypdb/clients/search/search_client.py
pypdb/clients/search/search_client_test.py
pypdb/clients/search/operators/__init__.py
pypdb/clients/search/operators/chemical_operators.py
pypdb/clients/search/operators/chemical_operators_test.py
pypdb/clients/search/operators/seqmotif_operators.py
pypdb/clients/search/operators/seqmotif_operators_test.py
pypdb/clients/search/operators/sequence_operators.py
pypdb/clients/search/operators/sequence_operators_test.py
pypdb/clients/search/operators/structure_operators.py
pypdb/clients/search/operators/structure_operators_test.py
pypdb/clients/search/operators/text_operators.py
pypdb/clients/search/operators/text_operators_test.py
pypdb/util/__init__.py
pypdb/util/http_requests.py
pypdb/util/test_http_requests.py
pypdb-2.4.dist-info/.ipynb_checkpoints/dependency_links-checkpoint.txt
pypdb-2.4.dist-info/LICENSE
pypdb-2.4.dist-info/METADATA
pypdb-2.4.dist-info/WHEEL
pypdb-2.4.dist-info/top_level.txt
pypdb-2.4.dist-info/RECORD
