Metadata-Version: 2.1
Name: pypdb
Version: 2.4
Summary: A Python wrapper for the RCSB Protein Data Bank (PDB) API
Home-page: https://github.com/williamgilpin/pypdb
Download-URL: https://github.com/williamgilpin/pypdb/tarball/0.6
Author: William Gilpin
Author-email: firstnamelastname@gmail.com
Keywords: protein,data,RESTful,api
License-File: LICENSE
Requires-Dist: requests
